ra2ce/README.md
ra2ce/__init__.py
ra2ce/__main__.py
ra2ce/analysis/README.md
ra2ce/analysis/__init__.py
ra2ce/analysis/adaptation/README.md
ra2ce/analysis/adaptation/__init__.py
ra2ce/analysis/adaptation/adaptation.py
ra2ce/analysis/adaptation/adaptation_option.py
ra2ce/analysis/adaptation/adaptation_option_analysis.py
ra2ce/analysis/adaptation/adaptation_option_collection.py
ra2ce/analysis/analysis_base.py
ra2ce/analysis/analysis_collection.py
ra2ce/analysis/analysis_config_data/README.md
ra2ce/analysis/analysis_config_data/__init__.py
ra2ce/analysis/analysis_config_data/analysis_config_data.py
ra2ce/analysis/analysis_config_data/analysis_config_data_reader.py
ra2ce/analysis/analysis_config_data/analysis_config_data_validator.py
ra2ce/analysis/analysis_config_data/enums/__init__.py
ra2ce/analysis/analysis_config_data/enums/analysis_damages_enum.py
ra2ce/analysis/analysis_config_data/enums/analysis_enum.py
ra2ce/analysis/analysis_config_data/enums/analysis_losses_enum.py
ra2ce/analysis/analysis_config_data/enums/damage_curve_enum.py
ra2ce/analysis/analysis_config_data/enums/event_type_enum.py
ra2ce/analysis/analysis_config_data/enums/loss_type_enum.py
ra2ce/analysis/analysis_config_data/enums/risk_calculation_mode_enum.py
ra2ce/analysis/analysis_config_data/enums/traffic_period_enum.py
ra2ce/analysis/analysis_config_data/enums/trip_purpose_enum.py
ra2ce/analysis/analysis_config_data/enums/weighing_enum.py
ra2ce/analysis/analysis_config_wrapper.py
ra2ce/analysis/analysis_factory.py
ra2ce/analysis/analysis_input_wrapper.py
ra2ce/analysis/analysis_protocol.py
ra2ce/analysis/analysis_result/__init__.py
ra2ce/analysis/analysis_result/analysis_result.py
ra2ce/analysis/analysis_result/analysis_result_wrapper.py
ra2ce/analysis/analysis_result/analysis_result_wrapper_exporter.py
ra2ce/analysis/analysis_result/analysis_result_wrapper_protocol.py
ra2ce/analysis/damages/__init__.py
ra2ce/analysis/damages/analysis_damages_protocol.py
ra2ce-1.0.0.dist-info/entry_points.txt
ra2ce-1.0.0.dist-info/WHEEL
ra2ce-1.0.0.dist-info/METADATA
ra2ce-1.0.0.dist-info/LICENSE
ra2ce-1.0.0.dist-info/RECORD
