Metadata-Version: 2.1
Name: ra2ce
Version: 1.0.0
Summary: Risk Assessment and Adaptation for Critical infrastructurE (RA2CE).
Home-page: https://github.com/Deltares/ra2ce
License: GPL-3.0-or-later
Author: Margreet van Marle
Author-email: Margreet.vanMarle@deltares.nl
Maintainer: Carles Salvador Soriano Perez
Maintainer-email: carles.sorianoperez@deltares.nl
Requires-Python: >=3.11,<3.12
Classifier: Development Status :: 2 - Pre-Alpha
Classifier: Intended Audience :: Developers
Classifier: License :: OSI Approved :: GNU General Public License v3 (GPLv3)
Classifier: License :: OSI Approved :: GNU General Public License v3 or later (GPLv3+)
Classifier: Natural Language :: English
Classifier: Programming Language :: Python :: 3
Classifier: Programming Language :: Python :: 3.11
Classifier: Programming Language :: Python :: 3
Classifier: Programming Language :: Python :: 3.11
Requires-Dist: Rtree (>=1.0.0,<2.0.0)
Requires-Dist: affine (>=2.3.1,<3.0.0)
Requires-Dist: click (>=8.1.3,<9.0.0)
Requires-Dist: geopandas (>=0.14.0,<0.15.0)
Requires-Dist: geopy (>=2.4.0,<3.0.0)
Requires-Dist: joblib (>=1.3.2,<2.0.0)
Requires-Dist: momepy (==0.5.0)
Requires-Dist: networkx (>=2.8.6,<3.0.0)
Requires-Dist: numpy (>=1.23.3,<2.0.0)
Requires-Dist: openpyxl (>=3.0.10,<4.0.0)
Requires-Dist: osmnx (>=1.6.0,<2.0.0)
Requires-Dist: pandas (>=1.4.4,<2.0.0)
Requires-Dist: pyarrow (>=10.0.0,<11.0.0)
Requires-Dist: pygeos (>=0.14,<0.15)
Requires-Dist: pyinstaller (>=6.2.0,<7.0.0)
Requires-Dist: pyogrio (>=0.6.0,<0.7.0)
Requires-Dist: rasterio (>=1.3.2,<2.0.0)
Requires-Dist: rasterstats (>=0.17.0,<0.18.0)
Requires-Dist: scipy (>=1.9.1,<2.0.0)
Requires-Dist: seaborn (>=0.12.0,<0.13.0)
Requires-Dist: shapely (>=2.0.1,<3.0.0)
Requires-Dist: snkit (>=1.9.0,<2.0.0)
Requires-Dist: tqdm (>=4.66.1,<5.0.0)
Requires-Dist: xarray (>=2022.6.0,<2023.0.0)
Requires-Dist: xlrd (>=2.0.1,<3.0.0)
Project-URL: Documentation, https://deltares.github.io/ra2ce/
Project-URL: Repository, https://github.com/Deltares/ra2ce
